conversational_sentence_encoder/__init__.py
conversational_sentence_encoder/definitions.py
conversational_sentence_encoder/vectorizers.py
conversational_sentence_encoder-0.0.6.dist-info/LICENSE
conversational_sentence_encoder-0.0.6.dist-info/METADATA
conversational_sentence_encoder-0.0.6.dist-info/WHEEL
conversational_sentence_encoder-0.0.6.dist-info/top_level.txt
conversational_sentence_encoder-0.0.6.dist-info/RECORD
