Metadata-Version: 2.1
Name: conversational-sentence-encoder
Version: 0.0.6
Summary: Dual sentence encoder package
Home-page: https://github.com/davidalami/ConveRT
Author: David Alami
Author-email: davidalami@gmail.com
License: UNKNOWN
Platform: UNKNOWN
Classifier: Programming Language :: Python :: 3
Classifier: License :: OSI Approved :: Apache Software License
Classifier: Operating System :: OS Independent
Requires-Python: >=3.7.0
License-File: LICENSE
Requires-Dist: tensorflow (==2.8.0)
Requires-Dist: tensorflow-hub (==0.12.0)
Requires-Dist: tensorflow-text (==2.8.2)
Requires-Dist: tf-sentencepiece (==0.1.90)
Requires-Dist: tqdm (==4.64.0)
